mcp_server_simplified.py
mcp_server_stdio.py
core/ragflow_api.py
ragflow_mcp-1.2.0.dist-info/METADATA
ragflow_mcp-1.2.0.dist-info/WHEEL
ragflow_mcp-1.2.0.dist-info/entry_points.txt
ragflow_mcp-1.2.0.dist-info/top_level.txt
ragflow_mcp-1.2.0.dist-info/RECORD
