Metadata-Version: 2.4
Name: ragflow-mcp
Version: 1.2.0
Summary: A mcp server that talk with my ragflow
Author: Cheson
Requires-Python: >=3.12
Requires-Dist: fastmcp
Requires-Dist: requests
Requires-Dist: httpx
